zula/__init__.py
zula/__version__.py
zula/db.py
zula-0.1.0.dist-info/METADATA
zula-0.1.0.dist-info/RECORD
zula-0.1.0.dist-info/WHEEL
zula-0.1.0.dist-info/top_level.txt
