Metadata-Version: 2.1
Name: zula
Version: 0.1.0
Summary: dead simple key-value and in-memory database built upon json package.
Home-page: https://github.com/efe/zula
Author: Efe Öge
Author-email: efeoge@gmail.com
License: MIT
Platform: UNKNOWN
Classifier: License :: OSI Approved :: MIT License
Classifier: Programming Language :: Python
Classifier: Programming Language :: Python :: 2
Classifier: Programming Language :: Python :: 3
Requires-Python: >=2.6
